spedextractor/__init__.py
spedextractor/__main__.py
spedextractor/build_csv.py
spedextractor/build_pythonsped_json.py
spedextractor/compare_pythonsped.py
spedextractor/constants.py
spedextractor/download.py
spedextractor/extract_tables.py
spedextractor/generate.py
spedextractor/get_table_headers.py
spedextractor/specs/2019/download_info.csv
spedextractor/specs/2019/ecd/ecd_accurate_fields.csv
spedextractor/specs/2019/ecd/ecd_fields.csv
spedextractor/specs/2019/ecd/ecd_pythonsped.json
spedextractor/specs/2019/ecd/ecd_registers.csv
spedextractor/specs/2019/ecf/ecf_accurate_fields.csv
spedextractor/specs/2019/ecf/ecf_fields.csv
spedextractor/specs/2019/ecf/ecf_pythonsped.json
spedextractor/specs/2019/ecf/ecf_registers.csv
spedextractor/specs/2019/efd_icms_ipi/efd_icms_ipi_accurate_fields.csv
spedextractor/specs/2019/efd_icms_ipi/efd_icms_ipi_fields.csv
spedextractor/specs/2019/efd_icms_ipi/efd_icms_ipi_pythonsped.json
spedextractor/specs/2019/efd_icms_ipi/efd_icms_ipi_registers.csv
spedextractor/specs/2019/efd_pis_cofins/efd_pis_cofins_accurate_fields.csv
spedextractor/specs/2019/efd_pis_cofins/efd_pis_cofins_fields.csv
spedextractor/specs/2019/efd_pis_cofins/efd_pis_cofins_pythonsped.json
spedextractor/specs/2019/efd_pis_cofins/efd_pis_cofins_registers.csv
spedextractor/specs/2019/pdf/ecd.pdf
spedextractor/specs/2019/pdf/ecf.pdf
spedextractor/specs/2019/pdf/efd_icms_ipi.pdf
spedextractor/specs/2019/pdf/efd_pis_cofins.pdf
spedextractor/specs/2020/download_info.csv
spedextractor/specs/2020/camelot_patch/ecd_camelot_patch.csv
spedextractor/specs/2020/camelot_patch/ecf_camelot_patch.csv
spedextractor/specs/2020/camelot_patch/efd_icms_ipi_camelot_patch.csv
spedextractor/specs/2020/camelot_patch/efd_pis_cofins_camelot_patch.csv
spedextractor/specs/2020/ecd/ecd_accurate_fields.csv
spedextractor/specs/2020/ecd/ecd_fields.csv
spedextractor/specs/2020/ecd/ecd_pythonsped.json
spedextractor/specs/2020/ecd/ecd_registers.csv
spedextractor/specs/2020/ecf/ecf_accurate_fields.csv
sped_extractor-1.0.5.dist-info/METADATA
sped_extractor-1.0.5.dist-info/WHEEL
sped_extractor-1.0.5.dist-info/top_level.txt
sped_extractor-1.0.5.dist-info/RECORD
