Metadata-Version: 2.1
Name: sped-extractor
Version: 1.0.5
Summary: Extrai e interpreta os registros e os campos das tabelas dos manuais do SPED (Sistema Público de Escrituração Digital), para os módulos ECD, ECF, EFD Contribuições (PIS, COFINS) e EFD ICMS IPI.
Home-page: https://github.com/akretion/sped-extractor
Author: Akretion
Author-email: contact@akretion.com.br
License: MIT
Platform: UNKNOWN
Classifier: Development Status :: 3 - Alpha
Classifier: License :: OSI Approved :: MIT License
Classifier: Programming Language :: Python :: 3
Classifier: Programming Language :: Python :: 3.7
Requires-Dist: camelot-py (>=0.8.0)
Requires-Dist: click
Requires-Dist: python-sped
Requires-Dist: unidecode
